odoo/addons/l10n_be_iso20022_pain/README.rst
odoo/addons/l10n_be_iso20022_pain/__init__.py
odoo/addons/l10n_be_iso20022_pain/__manifest__.py
odoo/addons/l10n_be_iso20022_pain/i18n/fr.po
odoo/addons/l10n_be_iso20022_pain/i18n/l10n_be_iso20022_pain.pot
odoo/addons/l10n_be_iso20022_pain/models/__init__.py
odoo/addons/l10n_be_iso20022_pain/models/account_move.py
odoo/addons/l10n_be_iso20022_pain/models/account_move_line.py
odoo/addons/l10n_be_iso20022_pain/models/account_payment_line.py
odoo/addons/l10n_be_iso20022_pain/static/description/icon.png
odoo/addons/l10n_be_iso20022_pain/tests/__init__.py
odoo/addons/l10n_be_iso20022_pain/tests/test_l10n_be_iso20022_pain.py
odoo13_addon_l10n_be_iso20022_pain-13.0.1.0.1.dist-info/METADATA
odoo13_addon_l10n_be_iso20022_pain-13.0.1.0.1.dist-info/WHEEL
odoo13_addon_l10n_be_iso20022_pain-13.0.1.0.1.dist-info/top_level.txt
odoo13_addon_l10n_be_iso20022_pain-13.0.1.0.1.dist-info/RECORD
